README.md
setup.py
LogRegrWrapperClass/LogRegrWrapperClass.py
LogRegrWrapperClass/TestClasswithfileSampleFile.py
LogRegrWrapperClass/__init__.py
LogRegrWrapperClass/unit_test_logregr.py
LogRegrWrapperClass.egg-info/PKG-INFO
LogRegrWrapperClass.egg-info/SOURCES.txt
LogRegrWrapperClass.egg-info/dependency_links.txt
LogRegrWrapperClass.egg-info/not-zip-safe
LogRegrWrapperClass.egg-info/top_level.txt