Metadata-Version: 1.0
Name: LogRegrWrapperClass
Version: 0.2
Summary: Take home test Logistic Regression Wrapper class
Home-page: http://github.com/padvyas/LogRegrWrapperClass
Author: Padmapriya S
Author-email: padmapriya.sethuraman@gmail.com
License: MIT
Platform: UNKNOWN
